fastchunker_hq/__init__.py
fastchunker_hq/base.py
fastchunker_hq/md_chunker.py
fastchunker_hq/text_chunker.py
fastchunker_hq-0.1.0.dist-info/METADATA
fastchunker_hq-0.1.0.dist-info/WHEEL
fastchunker_hq-0.1.0.dist-info/top_level.txt
fastchunker_hq-0.1.0.dist-info/RECORD
