Metadata-Version: 2.4
Name: fastchunker-hq
Version: 0.1.0
Summary: Add your description here
Requires-Python: >=3.10
Requires-Dist: beautifulsoup4>=4.14.2
Requires-Dist: python-docx>=1.1.2
Requires-Dist: mammoth>=1.8.0
